hi_jeong/__init__.py
hi_jeong/hello.py
hi_jeong-0.8.0.dist-info/METADATA
hi_jeong-0.8.0.dist-info/WHEEL
hi_jeong-0.8.0.dist-info/entry_points.txt
hi_jeong-0.8.0.dist-info/top_level.txt
hi_jeong-0.8.0.dist-info/RECORD
