Metadata-Version: 2.1
Name: hi_jeong
Version: 0.8.0
Summary: Default template for PDM package
Author-email: Jeonghoon2 <ukidd12@naver.com>
License: MIT
Requires-Python: ==3.12.*
